identify/__init__.py
identify/cli.py
identify/extensions.py
identify/identify.py
identify/interpreters.py
identify/py.typed
identify/vendor/__init__.py
identify/vendor/licenses.py
identify-2.6.11.dist-info/LICENSE
identify-2.6.11.dist-info/METADATA
identify-2.6.11.dist-info/WHEEL
identify-2.6.11.dist-info/entry_points.txt
identify-2.6.11.dist-info/top_level.txt
identify-2.6.11.dist-info/RECORD
