Metadata-Version: 2.1
Name: identify
Version: 2.6.11
Summary: File identification library for Python
Home-page: https://github.com/pre-commit/identify
Author: Chris Kuehl
Author-email: ckuehl@ocf.berkeley.edu
License: MIT
Classifier: Programming Language :: Python :: 3
Classifier: Programming Language :: Python :: 3 :: Only
Classifier: Programming Language :: Python :: Implementation :: CPython
Classifier: Programming Language :: Python :: Implementation :: PyPy
Requires-Python: >=3.9
License-File: LICENSE
Provides-Extra: license
Requires-Dist: ukkonen; extra == "license"
